pithy_cli/ai_commit.py
pithy_cli/cli.py
pithy_cli/git.py
pithy_cli/init.py
pithy_cli/keys.py
pithy_cli/llm.py
pithy_cli/prompt.py
pithy_cli/summarize.py
pithy_cli/default_prompts/commit-summary.md
pithy_cli/default_prompts/commit-titles.md
pithy_cli/default_prompts/file-summary.md
pithy_cli-0.1.4.dist-info/licenses/LICENSE
pithy_cli-0.1.4.dist-info/METADATA
pithy_cli-0.1.4.dist-info/WHEEL
pithy_cli-0.1.4.dist-info/entry_points.txt
pithy_cli-0.1.4.dist-info/top_level.txt
pithy_cli-0.1.4.dist-info/RECORD
