Metadata-Version: 2.4
Name: pithy-cli
Version: 0.1.4
Summary: Your pithy python pair programmer CLI tool
Requires-Python: >=3.12
License-File: LICENSE
Requires-Dist: anthropic>=0.69.0
Requires-Dist: argon2-cffi>=25.1.0
Requires-Dist: cryptography>=46.0.2
Requires-Dist: gitpython>=3.1.45
Requires-Dist: openai>=2.1.0
Requires-Dist: rich>=14.1.0
Requires-Dist: typer>=0.19.2
Provides-Extra: dev
Requires-Dist: pytest>=8.0.0; extra == "dev"
Requires-Dist: pytest-cov>=4.0.0; extra == "dev"
Requires-Dist: pre-commit>=4.0.0; extra == "dev"
Requires-Dist: ruff>=0.8.0; extra == "dev"
Requires-Dist: mypy>=1.13.0; extra == "dev"
Dynamic: license-file
